embedded_adaptive_stacking_keras/__init__.py
embedded_adaptive_stacking_keras/loss.py
embedded_adaptive_stacking_keras/models.py
embedded_adaptive_stacking_keras/optimizer.py
embedded_adaptive_stacking_keras/utils.py
embedded_adaptive_stacking_keras/visualization.py
embedded_adaptive_stacking_keras-0.7.dist-info/METADATA
embedded_adaptive_stacking_keras-0.7.dist-info/WHEEL
embedded_adaptive_stacking_keras-0.7.dist-info/top_level.txt
embedded_adaptive_stacking_keras-0.7.dist-info/RECORD
